rsequence.cpython-310-darwin.so
rsequence-0.0.1.dist-info/LICENSE.txt
rsequence-0.0.1.dist-info/METADATA
rsequence-0.0.1.dist-info/WHEEL
rsequence-0.0.1.dist-info/top_level.txt
rsequence-0.0.1.dist-info/RECORD
